{
  "items": [
    {
      "id": "test_bulletin_2pages.pdf",
      "date": "2026.04.20",
      "title": "4월 셋째주 ",
      "filename": "test_bulletin_2pages.pdf",
      "url": "/bulletins/test_bulletin_2pages.pdf",
      "uploaded_at": "2026-05-04T07:15:56.213Z"
    },
    {
      "id": "20260503-1777868513859",
      "date": "20260503",
      "title": "5월 1주차 주보",
      "filename": "20260503-1777868513859.jpeg",
      "url": "/bulletins/20260503-1777868513859.jpeg",
      "uploaded_at": "2026-05-04T04:21:55.259Z"
    }
  ]
}
