{
  "items": [
    {
      "id": "image002.jpg",
      "date": "2025.05.17",
      "title": "5월 셋째 주 주보 (2)",
      "filename": "image002.jpg",
      "url": "/bulletins/image002.jpg",
      "uploaded_at": "2026-05-18T11:31:58.700Z"
    },
    {
      "id": "image001.jpg",
      "date": "2025.05.17",
      "title": "5월 셋째 주 주보 (1)",
      "filename": "image001.jpg",
      "url": "/bulletins/image001.jpg",
      "uploaded_at": "2026-05-18T11:31:56.867Z"
    },
    {
      "id": "20260517_광염교회_주보.pdf",
      "date": "2025.05.17",
      "title": "5월 셋째 주 주보",
      "filename": "20260517_광염교회_주보.pdf",
      "url": "/bulletins/20260517_광염교회_주보.pdf",
      "uploaded_at": "2026-05-18T11:27:31.829Z"
    }
  ]
}
